flask_comment/__init__.py
Flask_Comment-0.1.0.dist-info/LICENSE
Flask_Comment-0.1.0.dist-info/METADATA
Flask_Comment-0.1.0.dist-info/WHEEL
Flask_Comment-0.1.0.dist-info/top_level.txt
Flask_Comment-0.1.0.dist-info/RECORD
