Metadata-Version: 2.1
Name: Flask-Comment
Version: 0.1.0
Summary: Create comment component in Flask/Jinja2 template.
Home-page: https://github.com/yuxiaoy1/flask_comment
Author: Frank Yu
Author-email: withyuxiaoy@gmail.com
License: MIT
Project-URL: Documentation, https://flask-comment.readthedocs.io
Project-URL: Source, https://github.com/yuxiaoy1/flask_comment
Project-URL: Changelog, https://flask-comment.readthedocs.io/en/latest/changelog.html
Project-URL: Issue Tracker, https://github.com/yuxiaoy1/flask_comment/issues
Keywords: flask,comment,extension
Platform: any
Classifier: Development Status :: 3 - Alpha
Classifier: Environment :: Web Environment
Classifier: Framework :: Flask
Classifier: Intended Audience :: Developers
Classifier: Programming Language :: Python :: 3 :: Only
Classifier: Programming Language :: Python :: 3.7
Classifier: Programming Language :: Python :: 3.8
Classifier: Programming Language :: Python :: 3.9
Classifier: License :: OSI Approved :: MIT License
Classifier: Topic :: Internet :: WWW/HTTP :: Dynamic Content
Classifier: Topic :: Software Development :: Libraries :: Python Modules
Requires-Python: >=3.6
License-File: LICENSE
Requires-Dist: Flask
Provides-Extra: dev
Requires-Dist: coverage ; extra == 'dev'
Requires-Dist: flake8 ; extra == 'dev'
Requires-Dist: tox ; extra == 'dev'
